{
	"name": "Pipeline Load All NYC Payroll Data",
	"properties": {
		"activities": [
			{
				"name": "DataFlow Load Payroll Data DB",
				"description": "Pipeline to load NYC Payroll Data from azure data lake storage to NYC SQL DB",
				"type": "ExecuteDataFlow",
				"dependsOn": [],
				"policy": {
					"timeout": "0.12:00:00",
					"retry": 0,
					"retryIntervalInSeconds": 30,
					"secureOutput": false,
					"secureInput": false
				},
				"userProperties": [],
				"typeProperties": {
					"dataflow": {
						"referenceName": "Load Payroll Data",
						"type": "DataFlowReference"
					},
					"compute": {
						"coreCount": 8,
						"computeType": "General"
					},
					"traceLevel": "Fine"
				}
			},
			{
				"name": "DataFlow Load Payroll data ASA",
				"description": "Load payroll data from NYC sql DB to synapse analytics table",
				"type": "ExecuteDataFlow",
				"dependsOn": [
					{
						"activity": "DataFlow Load Payroll Data DB",
						"dependencyConditions": [
							"Succeeded"
						]
					}
				],
				"policy": {
					"timeout": "0.12:00:00",
					"retry": 0,
					"retryIntervalInSeconds": 30,
					"secureOutput": false,
					"secureInput": false
				},
				"userProperties": [],
				"typeProperties": {
					"dataflow": {
						"referenceName": "Load Payroll sqlDB to Synapse",
						"type": "DataFlowReference"
					},
					"staging": {
						"linkedService": {
							"referenceName": "ls_adls",
							"type": "LinkedServiceReference"
						},
						"folderPath": "adlsnycpayroll-chukwubuikem-n/dirstaging"
					},
					"compute": {
						"coreCount": 8,
						"computeType": "General"
					},
					"traceLevel": "Fine"
				}
			},
			{
				"name": "DataFlow Load Title MD",
				"description": "Load employee title data from azure datalake to synapse analytics",
				"type": "ExecuteDataFlow",
				"dependsOn": [],
				"policy": {
					"timeout": "0.12:00:00",
					"retry": 0,
					"retryIntervalInSeconds": 30,
					"secureOutput": false,
					"secureInput": false
				},
				"userProperties": [],
				"typeProperties": {
					"dataflow": {
						"referenceName": "Load Title Data",
						"type": "DataFlowReference"
					},
					"staging": {
						"linkedService": {
							"referenceName": "ls_adls",
							"type": "LinkedServiceReference"
						},
						"folderPath": "adlsnycpayroll-chukwubuikem-n/dirstaging"
					},
					"compute": {
						"coreCount": 8,
						"computeType": "General"
					},
					"traceLevel": "Fine"
				}
			},
			{
				"name": "DataFlow Load Agency MD",
				"description": "Load agency master data from azure data lake to synapse analytics",
				"type": "ExecuteDataFlow",
				"dependsOn": [],
				"policy": {
					"timeout": "0.12:00:00",
					"retry": 0,
					"retryIntervalInSeconds": 30,
					"secureOutput": false,
					"secureInput": false
				},
				"userProperties": [],
				"typeProperties": {
					"dataflow": {
						"referenceName": "Load Agency Data",
						"type": "DataFlowReference"
					},
					"staging": {
						"linkedService": {
							"referenceName": "ls_adls",
							"type": "LinkedServiceReference"
						},
						"folderPath": "adlsnycpayroll-chukwubuikem-n/dirstaging"
					},
					"compute": {
						"coreCount": 8,
						"computeType": "General"
					},
					"traceLevel": "Fine"
				}
			},
			{
				"name": "DataFlow load Emp MD",
				"description": "Load employee master data from azure data lake storage to synapse analytics",
				"type": "ExecuteDataFlow",
				"dependsOn": [],
				"policy": {
					"timeout": "0.12:00:00",
					"retry": 0,
					"retryIntervalInSeconds": 30,
					"secureOutput": false,
					"secureInput": false
				},
				"userProperties": [],
				"typeProperties": {
					"dataflow": {
						"referenceName": "Load Emp Data",
						"type": "DataFlowReference"
					},
					"staging": {
						"linkedService": {
							"referenceName": "ls_adls",
							"type": "LinkedServiceReference"
						},
						"folderPath": "adlsnycpayroll-chukwubuikem-n/dirstaging"
					},
					"compute": {
						"coreCount": 8,
						"computeType": "General"
					},
					"traceLevel": "Fine"
				}
			}
		],
		"annotations": [],
		"lastPublishTime": "2023-09-03T02:08:45Z"
	},
	"type": "Microsoft.DataFactory/factories/pipelines"
}